{
    "backend": "django",
    "db_name": "",
    "db_pass": "",
    "db_type": "mysql",
    "db_user": "",
    "dbms": "1",
    "description": "generated product",
    "design": "material-dashboard",
    "docker": "1",
    "err_code": 0,
    "frontend": "",
    "heroku": "0",
    "pattern": "mvc",
    "pro": "0",
    "task_id": "9e6eb4a8-af0f-4995-8a9c-004f8329d3c0",
    "task_info": "Upload Sources [0%] - 392 files",
    "task_output": "9e6eb4a8-af0f-4995-8a9c-004f8329d3c0.zip",
    "task_result": "SUCCESS",
    "task_state": "RUNNING",
    "task_ts_end": "2024-03-05-09-01-47",
    "task_ts_start": "2024-03-05-09-01-44"
}